fynd/__init__.py
fynd-1.3.0.dist-info/METADATA
fynd-1.3.0.dist-info/RECORD
fynd-1.3.0.dist-info/WHEEL
fynd-1.3.0.dist-info/top_level.txt
