Metadata-Version: 2.1
Name: fynd
Version: 1.3.0
Summary: A super simple string searching library for complex list/dict structures
Home-page: https://github.com/ahmednooor/fynd
Author: Ahmed Noor
Author-email: m.ahmednoor7@yahoo.com
License: UNKNOWN
Platform: UNKNOWN
Classifier: Programming Language :: Python :: 3
Classifier: License :: OSI Approved :: MIT License
Classifier: Operating System :: OS Independent
